LICENSE
README.md
setup.py
sangreal_db/__init__.py
sangreal_db/utils.py
sangreal_db.egg-info/PKG-INFO
sangreal_db.egg-info/SOURCES.txt
sangreal_db.egg-info/dependency_links.txt
sangreal_db.egg-info/requires.txt
sangreal_db.egg-info/top_level.txt
sangreal_db/core/__init__.py
sangreal_db/core/database.py
sangreal_db/orm/__init__.py
sangreal_db/orm/query.py
sangreal_db/orm/session.py
sangreal_db/tests/__init__.py
sangreal_db/tests/test_core.py