Metadata-Version: 2.1
Name: sangreal-db
Version: 0.0.43
Summary: dataapi for database
Home-page: https://github.com/liubola/sangreal-db
Author: liubola
Author-email: lby3523@gmail.com
License: GNU General Public License v3.0
Platform: all
Classifier: Operating System :: OS Independent
Classifier: Intended Audience :: Developers
Classifier: License :: OSI Approved :: GNU General Public License v3 (GPLv3)
Classifier: Programming Language :: Python :: 3.11
Classifier: Topic :: Software Development :: Libraries
License-File: LICENSE
Requires-Dist: sqlalchemy>=2.0
Requires-Dist: pandas<=2.1.4
